grappa_http/__init__.py
grappa_http/plugin.py
grappa_http/adapters/__init__.py
grappa_http/adapters/aiohttp.py
grappa_http/adapters/base.py
grappa_http/adapters/requests.py
grappa_http/operators/__init__.py
grappa_http/operators/attributes.py
grappa_http/operators/base.py
grappa_http/operators/body.py
grappa_http/operators/content.py
grappa_http/operators/header.py
grappa_http/operators/json_body.py
grappa_http/operators/json_schema.py
grappa_http/operators/method.py
grappa_http/operators/status.py
grappa_http/operators/url.py
grappa_http/operators/url_parts.py
grappa_http-0.1.3.dist-info/DESCRIPTION.rst
grappa_http-0.1.3.dist-info/METADATA
grappa_http-0.1.3.dist-info/RECORD
grappa_http-0.1.3.dist-info/WHEEL
grappa_http-0.1.3.dist-info/metadata.json
grappa_http-0.1.3.dist-info/top_level.txt
tests/operators/__init__.py
tests/operators/body_test.py
tests/operators/conftest.py
tests/operators/content_test.py
tests/operators/header_test.py
tests/operators/json_body_test.py
tests/operators/json_schema_test.py
tests/operators/method_test.py
tests/operators/status_test.py
tests/operators/url_parts_test.py
tests/operators/url_test.py
